MANIFEST.in
README.md
setup.py
django_locator.egg-info/PKG-INFO
django_locator.egg-info/SOURCES.txt
django_locator.egg-info/dependency_links.txt
django_locator.egg-info/not-zip-safe
django_locator.egg-info/requires.txt
django_locator.egg-info/top_level.txt
locator/__init__.py
locator/admin.py
locator/models.py
locator/urls.py
locator/views.py
locator/fixtures/initial_data.json
locator/static/locator/css/map.css
locator/static/locator/js/jquery.storelocator.js
locator/templates/locator/locator.html
locator/templates/locator/templatetags/locator.html
locator/templatetags/__init__.py
locator/templatetags/locator.py