Metadata-Version: 1.1
Name: django-locator
Version: 1.0.0
Summary: An easy to integrate store locator plugin for Django.
Home-page: http://github.com/overshard/django-locator
Author: Isaac Bythewood
Author-email: isaac@bythewood.me
License: Simplified BSD
Download-URL: http://github.com/overshard/django-locator/downloads
Platform: UNKNOWN
Classifier: Development Status :: 5 - Production/Stable
Classifier: Environment :: Web Environment
Classifier: Intended Audience :: Developers
Classifier: License :: OSI Approved :: BSD License
Classifier: Operating System :: OS Independent
Classifier: Programming Language :: Python
Classifier: Framework :: Django
